{
"meta":{"test_sets":[],"test_metrics":[],"learn_metrics":[{"best_value":"Min","name":"RMSE"}],"launch_mode":"Train","parameters":"","iteration_count":600,"learn_sets":["learn"],"name":"experiment"},
"iterations":[
{"learn":[3923.540074],"iteration":0,"passed_time":0.07746366662,"remaining_time":46.40073631},
{"learn":[3813.584183],"iteration":1,"passed_time":0.1841213081,"remaining_time":55.05227112},
{"learn":[3706.03872],"iteration":2,"passed_time":0.2580301476,"remaining_time":51.34799937},
{"learn":[3601.575686],"iteration":3,"passed_time":0.3384326272,"remaining_time":50.42646146},
{"learn":[3500.941997],"iteration":4,"passed_time":0.442112993,"remaining_time":52.61144617},
{"learn":[3402.397097],"iteration":5,"passed_time":0.5209810815,"remaining_time":51.57712707},
{"learn":[3307.448685],"iteration":6,"passed_time":0.6044572627,"remaining_time":51.20616525},
{"learn":[3216.16342],"iteration":7,"passed_time":0.7712410157,"remaining_time":57.07183516},
{"learn":[3126.673713],"iteration":8,"passed_time":0.926493575,"remaining_time":60.83974476},
{"learn":[3040.785174],"iteration":9,"passed_time":1.006200283,"remaining_time":59.36581669},
{"learn":[2958.095411],"iteration":10,"passed_time":1.088963532,"remaining_time":58.30904731},
{"learn":[2876.472142],"iteration":11,"passed_time":1.218887824,"remaining_time":59.72550337},
{"learn":[2797.315025],"iteration":12,"passed_time":1.310117119,"remaining_time":59.15682685},
{"learn":[2720.891594],"iteration":13,"passed_time":1.415173874,"remaining_time":59.23513502},
{"learn":[2646.843268],"iteration":14,"passed_time":1.490488536,"remaining_time":58.12905289},
{"learn":[2575.105274],"iteration":15,"passed_time":1.569603039,"remaining_time":57.29051093},
{"learn":[2505.74923],"iteration":16,"passed_time":1.662262136,"remaining_time":57.00581324},
{"learn":[2437.992882],"iteration":17,"passed_time":1.74180634,"remaining_time":56.318405},
{"learn":[2372.035772],"iteration":18,"passed_time":1.826316052,"remaining_time":55.84682242},
{"learn":[2308.723751],"iteration":19,"passed_time":1.905534873,"remaining_time":55.26051132},
{"learn":[2247.455699],"iteration":20,"passed_time":1.984047737,"remaining_time":54.70303046},
{"learn":[2188.544643],"iteration":21,"passed_time":2.06159313,"remaining_time":54.16367405},
{"learn":[2131.643399],"iteration":22,"passed_time":2.140355586,"remaining_time":53.69500753},
{"learn":[2075.697921],"iteration":23,"passed_time":2.233606841,"remaining_time":53.60656419},
{"learn":[2021.185559],"iteration":24,"passed_time":2.317140026,"remaining_time":53.2942206},
{"learn":[1968.777301],"iteration":25,"passed_time":2.393379646,"remaining_time":52.83845833},
{"learn":[1918.4109],"iteration":26,"passed_time":2.480001191,"remaining_time":52.63113638},
{"learn":[1869.358555],"iteration":27,"passed_time":2.569678393,"remaining_time":52.4948586},
{"learn":[1822.438253],"iteration":28,"passed_time":2.651457333,"remaining_time":52.20628059},
{"learn":[1776.600845],"iteration":29,"passed_time":2.743397201,"remaining_time":52.12454681},
{"learn":[1732.447597],"iteration":30,"passed_time":2.832931578,"remaining_time":51.99800218},
{"learn":[1689.391075],"iteration":31,"passed_time":2.921021435,"remaining_time":51.84813048},
{"learn":[1647.540017],"iteration":32,"passed_time":3.029445326,"remaining_time":52.05137878},
{"learn":[1607.447061],"iteration":33,"passed_time":3.120728503,"remaining_time":51.95095096},
{"learn":[1568.607142],"iteration":34,"passed_time":3.21046054,"remaining_time":51.82600586},
{"learn":[1530.993259],"iteration":35,"passed_time":3.293940613,"remaining_time":51.6050696},
{"learn":[1494.181903],"iteration":36,"passed_time":3.375708812,"remaining_time":51.36551516},
{"learn":[1459.365148],"iteration":37,"passed_time":3.464518949,"remaining_time":51.23841183},
{"learn":[1425.341812],"iteration":38,"passed_time":3.553716377,"remaining_time":51.11884326},
{"learn":[1392.882647],"iteration":39,"passed_time":3.641635917,"remaining_time":50.98290284},
{"learn":[1361.270132],"iteration":40,"passed_time":3.7241492,"remaining_time":50.7755952},
{"learn":[1330.125707],"iteration":41,"passed_time":3.819248074,"remaining_time":50.74143869},
{"learn":[1300.671386],"iteration":42,"passed_time":3.899888959,"remaining_time":50.51716628},
{"learn":[1271.673852],"iteration":43,"passed_time":3.972782634,"remaining_time":50.20152602},
{"learn":[1243.678574],"iteration":44,"passed_time":4.052738043,"remaining_time":49.9837692},
{"learn":[1216.992339],"iteration":45,"passed_time":4.136477685,"remaining_time":49.81757908},
{"learn":[1191.441941],"iteration":46,"passed_time":4.221056803,"remaining_time":49.66477472},
{"learn":[1166.731019],"iteration":47,"passed_time":4.293532043,"remaining_time":49.37561849},
{"learn":[1142.930924],"iteration":48,"passed_time":4.364239349,"remaining_time":49.07542615},
{"learn":[1120.058141],"iteration":49,"passed_time":4.439179921,"remaining_time":48.83097913},
{"learn":[1097.844116],"iteration":50,"passed_time":4.515604791,"remaining_time":48.60915746},
{"learn":[1076.705749],"iteration":51,"passed_time":4.595252861,"remaining_time":48.42689553},
{"learn":[1056.305727],"iteration":52,"passed_time":4.672321913,"remaining_time":48.22188843},
{"learn":[1036.179373],"iteration":53,"passed_time":4.747368675,"remaining_time":48.00117216},
{"learn":[1017.47739],"iteration":54,"passed_time":4.824254143,"remaining_time":47.80397287},
{"learn":[999.2285197],"iteration":55,"passed_time":4.899304171,"remaining_time":47.59324052},
{"learn":[981.7529249],"iteration":56,"passed_time":4.974468206,"remaining_time":47.38835501},
{"learn":[964.8993378],"iteration":57,"passed_time":5.050103324,"remaining_time":47.19234486},
{"learn":[948.6029667],"iteration":58,"passed_time":5.137692649,"remaining_time":47.11002921},
{"learn":[933.1986806],"iteration":59,"passed_time":5.240536257,"remaining_time":47.16482632},
{"learn":[918.0957153],"iteration":60,"passed_time":5.321661932,"remaining_time":47.02255379},
{"learn":[903.4493964],"iteration":61,"passed_time":5.398961709,"remaining_time":46.84905483},
{"learn":[889.4500097],"iteration":62,"passed_time":5.478578307,"remaining_time":46.69835795},
{"learn":[876.451464],"iteration":63,"passed_time":5.556717177,"remaining_time":46.53750636},
{"learn":[863.6028878],"iteration":64,"passed_time":5.633452679,"remaining_time":46.36764897},
{"learn":[851.5394776],"iteration":65,"passed_time":5.710547784,"remaining_time":46.20352298},
{"learn":[839.8242788],"iteration":66,"passed_time":5.788213412,"remaining_time":46.04653356},
{"learn":[828.2186048],"iteration":67,"passed_time":5.863948408,"remaining_time":45.87677284},
{"learn":[817.3130188],"iteration":68,"passed_time":5.94023013,"remaining_time":45.71394491},
{"learn":[806.7862975],"iteration":69,"passed_time":6.015302614,"remaining_time":45.54443408},
{"learn":[796.8324742],"iteration":70,"passed_time":6.087989274,"remaining_time":45.35980741},
{"learn":[787.1504724],"iteration":71,"passed_time":6.164691187,"remaining_time":45.20773537},
{"learn":[778.0938375],"iteration":72,"passed_time":6.238628632,"remaining_time":45.03777108},
{"learn":[769.2460623],"iteration":73,"passed_time":6.318441328,"remaining_time":44.91216403},
{"learn":[760.7873689],"iteration":74,"passed_time":6.394784892,"remaining_time":44.76349424},
{"learn":[752.6877611],"iteration":75,"passed_time":6.471459684,"remaining_time":44.61901151},
{"learn":[744.8173839],"iteration":76,"passed_time":6.547734754,"remaining_time":44.47357502},
{"learn":[737.4658701],"iteration":77,"passed_time":6.626952091,"remaining_time":44.34960246},
{"learn":[730.5621443],"iteration":78,"passed_time":6.711525346,"remaining_time":44.26208487},
{"learn":[723.7997648],"iteration":79,"passed_time":6.795573446,"remaining_time":44.1712274},
{"learn":[717.433833],"iteration":80,"passed_time":6.880586591,"remaining_time":44.08672149},
{"learn":[711.1721134],"iteration":81,"passed_time":6.955357336,"remaining_time":43.93750122},
{"learn":[705.1629578],"iteration":82,"passed_time":7.031910963,"remaining_time":43.80118033},
{"learn":[699.3119113],"iteration":83,"passed_time":7.108794731,"remaining_time":43.66831049},
{"learn":[694.1011387],"iteration":84,"passed_time":7.186652589,"remaining_time":43.5426598},
{"learn":[688.8498783],"iteration":85,"passed_time":7.26144383,"remaining_time":43.39979219},
{"learn":[683.9070496],"iteration":86,"passed_time":7.339854539,"remaining_time":43.27983194},
{"learn":[678.9820253],"iteration":87,"passed_time":7.428286338,"remaining_time":43.21912051},
{"learn":[674.3638262],"iteration":88,"passed_time":7.514957497,"remaining_time":43.14767731},
{"learn":[669.9955452],"iteration":89,"passed_time":7.602263782,"remaining_time":43.07949477},
{"learn":[665.8307018],"iteration":90,"passed_time":7.683783615,"remaining_time":42.97852593},
{"learn":[661.8976152],"iteration":91,"passed_time":7.75446467,"remaining_time":42.818131},
{"learn":[658.0470754],"iteration":92,"passed_time":7.829127508,"remaining_time":42.68137254},
{"learn":[654.488058],"iteration":93,"passed_time":7.895723957,"remaining_time":42.50251407},
{"learn":[651.145503],"iteration":94,"passed_time":7.970424651,"remaining_time":42.36909946},
{"learn":[648.0113692],"iteration":95,"passed_time":8.04123118,"remaining_time":42.21646369},
{"learn":[644.8447194],"iteration":96,"passed_time":8.1070649,"remaining_time":42.0397283},
{"learn":[641.7041201],"iteration":97,"passed_time":8.175422842,"remaining_time":41.8781864},
{"learn":[638.8477833],"iteration":98,"passed_time":8.244130918,"remaining_time":41.72029889},
{"learn":[636.0399017],"iteration":99,"passed_time":8.325335115,"remaining_time":41.62667558},
{"learn":[633.4121095],"iteration":100,"passed_time":8.399304409,"remaining_time":41.49755346},
{"learn":[630.7670586],"iteration":101,"passed_time":8.465821528,"remaining_time":41.33312864},
{"learn":[628.3064971],"iteration":102,"passed_time":8.540487955,"remaining_time":41.20992732},
{"learn":[625.93015],"iteration":103,"passed_time":8.606921751,"remaining_time":41.04839604},
{"learn":[623.7110302],"iteration":104,"passed_time":8.679431701,"remaining_time":40.91732088},
{"learn":[621.5082],"iteration":105,"passed_time":8.757713828,"remaining_time":40.81425123},
{"learn":[619.5384092],"iteration":106,"passed_time":8.844793067,"remaining_time":40.7521774},
{"learn":[617.6649543],"iteration":107,"passed_time":8.912062816,"remaining_time":40.59939727},
{"learn":[615.7997248],"iteration":108,"passed_time":8.979249793,"remaining_time":40.44781329},
{"learn":[613.9856097],"iteration":109,"passed_time":9.044730969,"remaining_time":40.29016522},
{"learn":[612.2370748],"iteration":110,"passed_time":9.110191854,"remaining_time":40.13408844},
{"learn":[610.610701],"iteration":111,"passed_time":9.175340102,"remaining_time":39.97826759},
{"learn":[609.0516591],"iteration":112,"passed_time":9.244286926,"remaining_time":39.84042242},
{"learn":[607.5312361],"iteration":113,"passed_time":9.312667827,"remaining_time":39.70137337},
{"learn":[606.2508138],"iteration":114,"passed_time":9.380321022,"remaining_time":39.56048431},
{"learn":[604.8658255],"iteration":115,"passed_time":9.444456051,"remaining_time":39.4061787},
{"learn":[603.4866833],"iteration":116,"passed_time":9.510290047,"remaining_time":39.26042814},
{"learn":[602.3224945],"iteration":117,"passed_time":9.575148958,"remaining_time":39.11204913},
{"learn":[601.1658426],"iteration":118,"passed_time":9.643694007,"remaining_time":38.97997325},
{"learn":[599.9775443],"iteration":119,"passed_time":9.710005231,"remaining_time":38.84002092},
{"learn":[598.8769484],"iteration":120,"passed_time":9.776639541,"remaining_time":38.70256479},
{"learn":[597.8441115],"iteration":121,"passed_time":9.840925967,"remaining_time":38.55707059},
{"learn":[596.8095419],"iteration":122,"passed_time":9.908270032,"remaining_time":38.42475451},
{"learn":[595.8294217],"iteration":123,"passed_time":9.972805147,"remaining_time":38.28270363},
{"learn":[594.9117656],"iteration":124,"passed_time":10.04013679,"remaining_time":38.1525198},
{"learn":[594.0238197],"iteration":125,"passed_time":10.10396254,"remaining_time":38.01014479},
{"learn":[593.1497967],"iteration":126,"passed_time":10.16731116,"remaining_time":37.86722974},
{"learn":[592.3078001],"iteration":127,"passed_time":10.23981969,"remaining_time":37.75933509},
{"learn":[591.5640626],"iteration":128,"passed_time":10.32049379,"remaining_time":37.6818029},
{"learn":[590.8240766],"iteration":129,"passed_time":10.39411638,"remaining_time":37.57872846},
{"learn":[590.1234427],"iteration":130,"passed_time":10.47093783,"remaining_time":37.48755606},
{"learn":[589.3824243],"iteration":131,"passed_time":10.54163327,"remaining_time":37.37488159},
{"learn":[588.7035103],"iteration":132,"passed_time":10.60884292,"remaining_time":37.25059883},
{"learn":[588.0653781],"iteration":133,"passed_time":10.67490682,"remaining_time":37.12318343},
{"learn":[587.4441471],"iteration":134,"passed_time":10.75186254,"remaining_time":37.03419318},
{"learn":[586.7951237],"iteration":135,"passed_time":10.82642725,"remaining_time":36.93722239},
{"learn":[586.2157534],"iteration":136,"passed_time":10.90239946,"remaining_time":36.8453354},
{"learn":[585.6914899],"iteration":137,"passed_time":10.9789345,"remaining_time":36.75556332},
{"learn":[585.1502305],"iteration":138,"passed_time":11.05757515,"remaining_time":36.67296508},
{"learn":[584.6704132],"iteration":139,"passed_time":11.13818633,"remaining_time":36.59689794},
{"learn":[584.205329],"iteration":140,"passed_time":11.21205786,"remaining_time":36.49882664},
{"learn":[583.7012737],"iteration":141,"passed_time":11.30714044,"remaining_time":36.46950929},
{"learn":[583.222937],"iteration":142,"passed_time":11.40638448,"remaining_time":36.45257137},
{"learn":[582.746204],"iteration":143,"passed_time":11.48454868,"remaining_time":36.36773748},
{"learn":[582.3103533],"iteration":144,"passed_time":11.61293591,"remaining_time":36.44059199},
{"learn":[581.8996571],"iteration":145,"passed_time":11.69447261,"remaining_time":36.36500388},
{"learn":[581.4865566],"iteration":146,"passed_time":11.77110889,"remaining_time":36.27423351},
{"learn":[581.1063573],"iteration":147,"passed_time":12.01267633,"remaining_time":36.68736285},
{"learn":[580.6952838],"iteration":148,"passed_time":12.15620895,"remaining_time":36.79496804},
{"learn":[580.3830185],"iteration":149,"passed_time":12.22133954,"remaining_time":36.66401861},
{"learn":[580.0081895],"iteration":150,"passed_time":12.28835308,"remaining_time":36.53953995},
{"learn":[579.6587496],"iteration":151,"passed_time":12.35446313,"remaining_time":36.4131545},
{"learn":[579.3577453],"iteration":152,"passed_time":12.41832357,"remaining_time":36.28098455},
{"learn":[578.9915992],"iteration":153,"passed_time":12.48745574,"remaining_time":36.16496923},
{"learn":[578.6615343],"iteration":154,"passed_time":12.55593446,"remaining_time":36.04768282},
{"learn":[578.373022],"iteration":155,"passed_time":12.61816301,"remaining_time":35.91323317},
{"learn":[578.0520134],"iteration":156,"passed_time":12.68247698,"remaining_time":35.7855879},
{"learn":[577.7600901],"iteration":157,"passed_time":12.74886653,"remaining_time":35.66455069},
{"learn":[577.4657876],"iteration":158,"passed_time":12.82774779,"remaining_time":35.57884764},
{"learn":[577.1852784],"iteration":159,"passed_time":12.89406527,"remaining_time":35.4586795},
{"learn":[576.9168011],"iteration":160,"passed_time":12.96084097,"remaining_time":35.34042973},
{"learn":[576.6378024],"iteration":161,"passed_time":13.02973501,"remaining_time":35.22854279},
{"learn":[576.3725454],"iteration":162,"passed_time":13.09560396,"remaining_time":35.10907319},
{"learn":[576.1228765],"iteration":163,"passed_time":13.1619749,"remaining_time":34.9915918},
{"learn":[575.9132772],"iteration":164,"passed_time":13.2278323,"remaining_time":34.87337605},
{"learn":[575.664494],"iteration":165,"passed_time":13.29502254,"remaining_time":34.75927579},
{"learn":[575.4360742],"iteration":166,"passed_time":13.36108328,"remaining_time":34.64280874},
{"learn":[575.1724997],"iteration":167,"passed_time":13.43429976,"remaining_time":34.54534223},
{"learn":[574.9424793],"iteration":168,"passed_time":13.50113885,"remaining_time":34.43189849},
{"learn":[574.6879235],"iteration":169,"passed_time":13.5697952,"remaining_time":34.32359962},
{"learn":[574.4905854],"iteration":170,"passed_time":13.63597992,"remaining_time":34.20956366},
{"learn":[574.320001],"iteration":171,"passed_time":13.70077452,"remaining_time":34.09262496},
{"learn":[574.1213613],"iteration":172,"passed_time":13.78816906,"remaining_time":34.03207046},
{"learn":[573.9047752],"iteration":173,"passed_time":13.85689391,"remaining_time":33.92549887},
{"learn":[573.7010615],"iteration":174,"passed_time":13.92645794,"remaining_time":33.82139786},
{"learn":[573.506802],"iteration":175,"passed_time":13.99203775,"remaining_time":33.70809095},
{"learn":[573.2622198],"iteration":176,"passed_time":14.06220182,"remaining_time":33.60627893},
{"learn":[573.1199582],"iteration":177,"passed_time":14.12538292,"remaining_time":33.48826737},
{"learn":[572.9451013],"iteration":178,"passed_time":14.19475988,"remaining_time":33.38544082},
{"learn":[572.7665176],"iteration":179,"passed_time":14.26190215,"remaining_time":33.27777169},
{"learn":[572.562284],"iteration":180,"passed_time":14.32641878,"remaining_time":33.16447221},
{"learn":[572.4195082],"iteration":181,"passed_time":14.40077882,"remaining_time":33.07431618},
{"learn":[572.2774214],"iteration":182,"passed_time":14.46556739,"remaining_time":32.96252241},
{"learn":[572.0640875],"iteration":183,"passed_time":14.53138165,"remaining_time":32.85355852},
{"learn":[571.8836231],"iteration":184,"passed_time":14.60124074,"remaining_time":32.75413463},
{"learn":[571.6724406],"iteration":185,"passed_time":14.66752189,"remaining_time":32.64706486},
{"learn":[571.5092583],"iteration":186,"passed_time":14.74215454,"remaining_time":32.55887606},
{"learn":[571.4004081],"iteration":187,"passed_time":14.81712347,"remaining_time":32.47156846},
{"learn":[571.2342563],"iteration":188,"passed_time":14.89066861,"remaining_time":32.38129524},
{"learn":[571.0625684],"iteration":189,"passed_time":14.96598313,"remaining_time":32.29501622},
{"learn":[570.9012376],"iteration":190,"passed_time":15.04266875,"remaining_time":32.21178805},
{"learn":[570.8080223],"iteration":191,"passed_time":15.12068056,"remaining_time":32.13144618},
{"learn":[570.6765508],"iteration":192,"passed_time":15.19869078,"remaining_time":32.05112512},
{"learn":[570.515066],"iteration":193,"passed_time":15.27308742,"remaining_time":31.96326542},
{"learn":[570.3956995],"iteration":194,"passed_time":15.35088746,"remaining_time":31.88261241},
{"learn":[570.2872595],"iteration":195,"passed_time":15.42453487,"remaining_time":31.79342902},
{"learn":[570.1464754],"iteration":196,"passed_time":15.50077656,"remaining_time":31.70971043},
{"learn":[570.0120034],"iteration":197,"passed_time":15.57516193,"remaining_time":31.62229846},
{"learn":[569.8977067],"iteration":198,"passed_time":15.66280396,"remaining_time":31.5617306},
{"learn":[569.7546465],"iteration":199,"passed_time":15.7570968,"remaining_time":31.5141936},
{"learn":[569.6498061],"iteration":200,"passed_time":15.84810719,"remaining_time":31.45967548},
{"learn":[569.5321184],"iteration":201,"passed_time":15.93093656,"remaining_time":31.38867699},
{"learn":[569.4271964],"iteration":202,"passed_time":16.00498757,"remaining_time":31.30039441},
{"learn":[569.2783737],"iteration":203,"passed_time":16.07098639,"remaining_time":31.19662064},
{"learn":[569.1756207],"iteration":204,"passed_time":16.13851799,"remaining_time":31.09616881},
{"learn":[569.0670875],"iteration":205,"passed_time":16.20486223,"remaining_time":30.99376563},
{"learn":[568.9135266],"iteration":206,"passed_time":16.27143889,"remaining_time":30.8921521},
{"learn":[568.8140841],"iteration":207,"passed_time":16.33545064,"remaining_time":30.7860416},
{"learn":[568.6890183],"iteration":208,"passed_time":16.4017163,"remaining_time":30.6845506},
{"learn":[568.5631452],"iteration":209,"passed_time":16.46809711,"remaining_time":30.58360892},
{"learn":[568.4266262],"iteration":210,"passed_time":16.53366996,"remaining_time":30.48150528},
{"learn":[568.2785091],"iteration":211,"passed_time":16.6176563,"remaining_time":30.41344643},
{"learn":[568.1569746],"iteration":212,"passed_time":16.69058069,"remaining_time":30.32513957},
{"learn":[568.0602021],"iteration":213,"passed_time":16.75709001,"remaining_time":30.22540534},
{"learn":[567.9759702],"iteration":214,"passed_time":16.82547228,"remaining_time":30.12933408},
{"learn":[567.8704477],"iteration":215,"passed_time":16.89887406,"remaining_time":30.04244277},
{"learn":[567.738885],"iteration":216,"passed_time":16.96423951,"remaining_time":29.94149185},
{"learn":[567.608816],"iteration":217,"passed_time":17.02991984,"remaining_time":29.84141917},
{"learn":[567.5084795],"iteration":218,"passed_time":17.09781531,"remaining_time":29.7455143},
{"learn":[567.4216772],"iteration":219,"passed_time":17.16387279,"remaining_time":29.64668936},
{"learn":[567.278376],"iteration":220,"passed_time":17.23250137,"remaining_time":29.55257023},
{"learn":[567.2112604],"iteration":221,"passed_time":17.30040823,"remaining_time":29.45745185},
{"learn":[567.0950335],"iteration":222,"passed_time":17.36658077,"remaining_time":29.35964551},
{"learn":[566.9784352],"iteration":223,"passed_time":17.43184493,"remaining_time":29.26059684},
{"learn":[566.9101886],"iteration":224,"passed_time":17.49830845,"remaining_time":29.16384742},
{"learn":[566.8388009],"iteration":225,"passed_time":17.5778693,"remaining_time":29.08904035},
{"learn":[566.7770308],"iteration":226,"passed_time":17.65159896,"remaining_time":29.00460975},
{"learn":[566.6500342],"iteration":227,"passed_time":17.72759463,"remaining_time":28.92397018},
{"learn":[566.5984559],"iteration":228,"passed_time":17.79336621,"remaining_time":28.82680727},
{"learn":[566.4680131],"iteration":229,"passed_time":17.85807805,"remaining_time":28.72821252},
{"learn":[566.3899327],"iteration":230,"passed_time":17.9243675,"remaining_time":28.63243121},
{"learn":[566.2501918],"iteration":231,"passed_time":17.99091796,"remaining_time":28.53731814},
{"learn":[566.1228056],"iteration":232,"passed_time":18.05639517,"remaining_time":28.44075977},
{"learn":[566.0281322],"iteration":233,"passed_time":18.12314988,"remaining_time":28.3464652},
{"learn":[565.9517358],"iteration":234,"passed_time":18.18869898,"remaining_time":28.25053247},
{"learn":[565.8505553],"iteration":235,"passed_time":18.25419749,"remaining_time":28.15477918},
{"learn":[565.8032739],"iteration":236,"passed_time":18.32213082,"remaining_time":28.06301049},
{"learn":[565.7274916],"iteration":237,"passed_time":18.39104662,"remaining_time":27.97293646},
{"learn":[565.6417377],"iteration":238,"passed_time":18.45765522,"remaining_time":27.87955454},
{"learn":[565.5650485],"iteration":239,"passed_time":18.52695317,"remaining_time":27.79042976},
{"learn":[565.4750115],"iteration":240,"passed_time":18.59292134,"remaining_time":27.69650939},
{"learn":[565.3538023],"iteration":241,"passed_time":18.65965419,"remaining_time":27.60395123},
{"learn":[565.2255676],"iteration":242,"passed_time":18.73325896,"remaining_time":27.52170144},
{"learn":[565.1593674],"iteration":243,"passed_time":18.80762934,"remaining_time":27.44063953},
{"learn":[565.0208491],"iteration":244,"passed_time":18.88823429,"remaining_time":27.36866601},
{"learn":[564.9593755],"iteration":245,"passed_time":18.97126862,"remaining_time":27.30011825},
{"learn":[564.8757018],"iteration":246,"passed_time":19.04387804,"remaining_time":27.21655444},
{"learn":[564.7760179],"iteration":247,"passed_time":19.12151388,"remaining_time":27.14021325},
{"learn":[564.7161022],"iteration":248,"passed_time":19.19416693,"remaining_time":27.05683772},
{"learn":[564.6583414],"iteration":249,"passed_time":19.2648826,"remaining_time":26.97083564},
{"learn":[564.557119],"iteration":250,"passed_time":19.34114298,"remaining_time":26.89266494},
{"learn":[564.4788716],"iteration":251,"passed_time":19.41415346,"remaining_time":26.81002145},
{"learn":[564.4068993],"iteration":252,"passed_time":19.49087838,"remaining_time":26.73254861},
{"learn":[564.3284844],"iteration":253,"passed_time":19.56480305,"remaining_time":26.65126715},
{"learn":[564.2269403],"iteration":254,"passed_time":19.64038302,"remaining_time":26.57228291},
{"learn":[564.1057597],"iteration":255,"passed_time":19.71537262,"remaining_time":26.49253196},
{"learn":[564.0051168],"iteration":256,"passed_time":19.78752497,"remaining_time":26.40903138},
{"learn":[563.90431],"iteration":257,"passed_time":19.85962668,"remaining_time":26.32555164},
{"learn":[563.8132918],"iteration":258,"passed_time":19.92863985,"remaining_time":26.23809339},
{"learn":[563.7235592],"iteration":259,"passed_time":19.99843173,"remaining_time":26.15179534},
{"learn":[563.6890552],"iteration":260,"passed_time":20.06315625,"remaining_time":26.05904203},
{"learn":[563.6105753],"iteration":261,"passed_time":20.12762667,"remaining_time":25.96617486},
{"learn":[563.5235114],"iteration":262,"passed_time":20.19628797,"remaining_time":25.87889371},
{"learn":[563.4332841],"iteration":263,"passed_time":20.26492937,"remaining_time":25.79172829},
{"learn":[563.3825428],"iteration":264,"passed_time":20.32845622,"remaining_time":25.69823711},
{"learn":[563.2863727],"iteration":265,"passed_time":20.39769687,"remaining_time":25.61214569},
{"learn":[563.2358842],"iteration":266,"passed_time":20.46301423,"remaining_time":25.52128741},
{"learn":[563.183606],"iteration":267,"passed_time":20.52844779,"remaining_time":25.43076368},
{"learn":[563.1171174],"iteration":268,"passed_time":20.59752187,"remaining_time":25.34490609},
{"learn":[563.0413047],"iteration":269,"passed_time":20.66409628,"remaining_time":25.25611768},
{"learn":[562.9629138],"iteration":270,"passed_time":20.72856122,"remaining_time":25.16493226},
{"learn":[562.8948144],"iteration":271,"passed_time":20.79354409,"remaining_time":25.07456787},
{"learn":[562.852895],"iteration":272,"passed_time":20.85985596,"remaining_time":24.98598132},
{"learn":[562.7607311],"iteration":273,"passed_time":20.92986493,"remaining_time":24.90195608},
{"learn":[562.6952962],"iteration":274,"passed_time":20.99509613,"remaining_time":24.81238634},
{"learn":[562.6441311],"iteration":275,"passed_time":21.0588419,"remaining_time":24.72124918},
{"learn":[562.6010711],"iteration":276,"passed_time":21.12526417,"remaining_time":24.63343078},
{"learn":[562.5206169],"iteration":277,"passed_time":21.19163688,"remaining_time":24.54570891},
{"learn":[562.4056116],"iteration":278,"passed_time":21.26060784,"remaining_time":24.46112945},
{"learn":[562.3656836],"iteration":279,"passed_time":21.3301293,"remaining_time":24.37729063},
{"learn":[562.2748157],"iteration":280,"passed_time":21.39498749,"remaining_time":24.28825982},
{"learn":[562.2340377],"iteration":281,"passed_time":21.4625137,"remaining_time":24.20240907},
{"learn":[562.191379],"iteration":282,"passed_time":21.52699741,"remaining_time":24.11327978},
{"learn":[562.1360821],"iteration":283,"passed_time":21.59142407,"remaining_time":24.02426058},
{"learn":[562.0698508],"iteration":284,"passed_time":21.65814129,"remaining_time":23.93794563},
{"learn":[562.0086947],"iteration":285,"passed_time":21.72440334,"remaining_time":23.851268},
{"learn":[561.9375503],"iteration":286,"passed_time":21.79276449,"remaining_time":23.7670219},
{"learn":[561.8940192],"iteration":287,"passed_time":21.85886582,"remaining_time":23.68043797},
{"learn":[561.8272937],"iteration":288,"passed_time":21.92923016,"remaining_time":23.59858332},
{"learn":[561.7129601],"iteration":289,"passed_time":21.99645106,"remaining_time":23.51344769},
{"learn":[561.6764449],"iteration":290,"passed_time":22.06407953,"remaining_time":23.42886796},
{"learn":[561.6037955],"iteration":291,"passed_time":22.12676615,"remaining_time":23.33919169},
{"learn":[561.511593],"iteration":292,"passed_time":22.19300645,"remaining_time":23.25342314},
{"learn":[561.3673082],"iteration":293,"passed_time":22.36561941,"remaining_time":23.27850184},
{"learn":[561.3128779],"iteration":294,"passed_time":22.55456475,"remaining_time":23.31912626},
{"learn":[561.2497381],"iteration":295,"passed_time":22.62052326,"remaining_time":23.23188876},
{"learn":[561.1773561],"iteration":296,"passed_time":22.68814521,"remaining_time":23.14649158},
{"learn":[561.1238534],"iteration":297,"passed_time":22.76436076,"remaining_time":23.06992265},
{"learn":[561.0749945],"iteration":298,"passed_time":22.8384467,"remaining_time":22.99121223},
{"learn":[560.9743343],"iteration":299,"passed_time":22.91410348,"remaining_time":22.91410348},
{"learn":[560.8796074],"iteration":300,"passed_time":22.99144918,"remaining_time":22.83868207},
{"learn":[560.737694],"iteration":301,"passed_time":23.06300853,"remaining_time":22.75753822},
{"learn":[560.6929055],"iteration":302,"passed_time":23.13713923,"remaining_time":22.67897806},
{"learn":[560.6528943],"iteration":303,"passed_time":23.21521423,"remaining_time":22.60428754},
{"learn":[560.6163279],"iteration":304,"passed_time":23.29357961,"remaining_time":22.52985568},
{"learn":[560.5653927],"iteration":305,"passed_time":23.37137507,"remaining_time":22.45485056},
{"learn":[560.4855186],"iteration":306,"passed_time":23.44806265,"remaining_time":22.37876989},
{"learn":[560.4076053],"iteration":307,"passed_time":23.52271236,"remaining_time":22.30075328},
{"learn":[560.311496],"iteration":308,"passed_time":23.59832001,"remaining_time":22.22366059},
{"learn":[560.2740515],"iteration":309,"passed_time":23.67508809,"remaining_time":22.14766305},
{"learn":[560.2097735],"iteration":310,"passed_time":23.75092677,"remaining_time":22.0707969},
{"learn":[560.1610975],"iteration":311,"passed_time":23.82545245,"remaining_time":21.99272534},
{"learn":[560.1310249],"iteration":312,"passed_time":23.89909765,"remaining_time":21.91386909},
{"learn":[560.0065533],"iteration":313,"passed_time":23.97713831,"remaining_time":21.83904954},
{"learn":[559.9560023],"iteration":314,"passed_time":24.04279477,"remaining_time":21.75300479},
{"learn":[559.8714006],"iteration":315,"passed_time":24.10896209,"remaining_time":21.66754821},
{"learn":[559.7739704],"iteration":316,"passed_time":24.17333774,"remaining_time":21.58061382},
{"learn":[559.6776241],"iteration":317,"passed_time":24.24162202,"remaining_time":21.49728745},
{"learn":[559.6165051],"iteration":318,"passed_time":24.30775375,"remaining_time":21.41215926},
{"learn":[559.5595549],"iteration":319,"passed_time":24.3737416,"remaining_time":21.3270239},
{"learn":[559.5305708],"iteration":320,"passed_time":24.43903254,"remaining_time":21.24140211},
{"learn":[559.4866005],"iteration":321,"passed_time":24.505359,"remaining_time":21.15680062},
{"learn":[559.4184756],"iteration":322,"passed_time":24.57350785,"remaining_time":21.07387516},
{"learn":[559.3827178],"iteration":323,"passed_time":24.6556753,"remaining_time":21.00298267},
{"learn":[559.3357032],"iteration":324,"passed_time":24.73648959,"remaining_time":20.93087581},
{"learn":[559.2514996],"iteration":325,"passed_time":24.85645742,"remaining_time":20.89162372},
{"learn":[559.1834426],"iteration":326,"passed_time":24.98226022,"remaining_time":20.85674936},
{"learn":[559.1128933],"iteration":327,"passed_time":25.08871694,"remaining_time":20.80527746},
{"learn":[559.0239193],"iteration":328,"passed_time":25.16580798,"remaining_time":20.72928256},
{"learn":[558.9715665],"iteration":329,"passed_time":25.23783256,"remaining_time":20.64913573},
{"learn":[558.9255757],"iteration":330,"passed_time":25.31105517,"remaining_time":20.57001161},
{"learn":[558.8949229],"iteration":331,"passed_time":25.38711098,"remaining_time":20.49321007},
{"learn":[558.8079049],"iteration":332,"passed_time":25.47567795,"remaining_time":20.42644448},
{"learn":[558.7006673],"iteration":333,"passed_time":25.54421539,"remaining_time":20.34359669},
{"learn":[558.6680051],"iteration":334,"passed_time":25.60907831,"remaining_time":20.25792762},
{"learn":[558.5612287],"iteration":335,"passed_time":25.67852707,"remaining_time":20.17598555},
{"learn":[558.5127661],"iteration":336,"passed_time":25.75242785,"remaining_time":20.09759206},
{"learn":[558.4485078],"iteration":337,"passed_time":25.82144962,"remaining_time":20.0154432},
{"learn":[558.4012931],"iteration":338,"passed_time":25.88953419,"remaining_time":19.93265022},
{"learn":[558.3501246],"iteration":339,"passed_time":25.95329515,"remaining_time":19.84663747},
{"learn":[558.2679654],"iteration":340,"passed_time":26.01586904,"remaining_time":19.75985361},
{"learn":[558.1742956],"iteration":341,"passed_time":26.08114209,"remaining_time":19.67524754},
{"learn":[558.1263328],"iteration":342,"passed_time":26.14642866,"remaining_time":19.59076433},
{"learn":[558.0340587],"iteration":343,"passed_time":26.21598381,"remaining_time":19.50956935},
{"learn":[557.9856399],"iteration":344,"passed_time":26.28048727,"remaining_time":19.42470798},
{"learn":[557.9030468],"iteration":345,"passed_time":26.34726635,"remaining_time":19.34163484},
{"learn":[557.8068996],"iteration":346,"passed_time":26.41402556,"remaining_time":19.25864111},
{"learn":[557.6983918],"iteration":347,"passed_time":26.48077602,"remaining_time":19.17573436},
{"learn":[557.6485245],"iteration":348,"passed_time":26.54667651,"remaining_time":19.09230889},
{"learn":[557.6089815],"iteration":349,"passed_time":26.61415496,"remaining_time":19.01011069},
{"learn":[557.5432249],"iteration":350,"passed_time":26.68497073,"remaining_time":18.93036385},
{"learn":[557.4414931],"iteration":351,"passed_time":26.75973428,"remaining_time":18.85344915},
{"learn":[557.3465086],"iteration":352,"passed_time":26.83116454,"remaining_time":18.77421428},
{"learn":[557.2567832],"iteration":353,"passed_time":26.90504785,"remaining_time":18.69672817},
{"learn":[557.1900713],"iteration":354,"passed_time":26.9883856,"remaining_time":18.62578725},
{"learn":[557.1136996],"iteration":355,"passed_time":27.06082681,"remaining_time":18.54730826},
{"learn":[557.0893155],"iteration":356,"passed_time":27.15430348,"remaining_time":18.48318136},
{"learn":[556.9597379],"iteration":357,"passed_time":27.2442088,"remaining_time":18.41647634},
{"learn":[556.8875261],"iteration":358,"passed_time":27.34855679,"remaining_time":18.35933757},
{"learn":[556.8078258],"iteration":359,"passed_time":27.44525543,"remaining_time":18.29683695},
{"learn":[556.6947367],"iteration":360,"passed_time":27.54106695,"remaining_time":18.23355956},
{"learn":[556.6439158],"iteration":361,"passed_time":27.65252205,"remaining_time":18.18038742},
{"learn":[556.5714871],"iteration":362,"passed_time":27.73775533,"remaining_time":18.10977414},
{"learn":[556.519341],"iteration":363,"passed_time":27.81955891,"remaining_time":18.03685688},
{"learn":[556.4819178],"iteration":364,"passed_time":27.96482553,"remaining_time":18.00475069},
{"learn":[556.417882],"iteration":365,"passed_time":28.06465153,"remaining_time":17.94297393},
{"learn":[556.3826132],"iteration":366,"passed_time":28.1345895,"remaining_time":17.86201459},
{"learn":[556.3319696],"iteration":367,"passed_time":28.20584481,"remaining_time":17.78194564},
{"learn":[556.2795059],"iteration":368,"passed_time":28.29283465,"remaining_time":17.71177454},
{"learn":[556.2043768],"iteration":369,"passed_time":28.38463629,"remaining_time":17.64450364},
{"learn":[556.0887499],"iteration":370,"passed_time":28.47386897,"remaining_time":17.57551481},
{"learn":[556.0654265],"iteration":371,"passed_time":28.55251633,"remaining_time":17.49992936},
{"learn":[556.0056178],"iteration":372,"passed_time":28.62298965,"remaining_time":17.41935295},
{"learn":[555.9267861],"iteration":373,"passed_time":28.69198783,"remaining_time":17.33793917},
{"learn":[555.8559039],"iteration":374,"passed_time":28.75604733,"remaining_time":17.2536284},
{"learn":[555.8154477],"iteration":375,"passed_time":28.82217864,"remaining_time":17.17065961},
{"learn":[555.7887453],"iteration":376,"passed_time":28.89095466,"remaining_time":17.08934453},
{"learn":[555.7228216],"iteration":377,"passed_time":28.95666728,"remaining_time":17.00629665},
{"learn":[555.6591551],"iteration":378,"passed_time":29.02779758,"remaining_time":16.92649938},
{"learn":[555.6330706],"iteration":379,"passed_time":29.09188954,"remaining_time":16.84267289},
{"learn":[555.5633769],"iteration":380,"passed_time":29.15514116,"remaining_time":16.75846697},
{"learn":[555.4790967],"iteration":381,"passed_time":29.22198133,"remaining_time":16.67641866},
{"learn":[555.3836193],"iteration":382,"passed_time":29.28856562,"remaining_time":16.5943048},
{"learn":[555.3179231],"iteration":383,"passed_time":29.35350141,"remaining_time":16.51134454},
{"learn":[555.2459361],"iteration":384,"passed_time":29.422922,"remaining_time":16.43098241},
{"learn":[555.1595756],"iteration":385,"passed_time":29.4899999,"remaining_time":16.34937818},
{"learn":[555.0996297],"iteration":386,"passed_time":29.55664677,"remaining_time":16.26761179},
{"learn":[555.06282],"iteration":387,"passed_time":29.62269497,"remaining_time":16.18559622},
{"learn":[555.0171711],"iteration":388,"passed_time":29.68708213,"remaining_time":16.10276177},
{"learn":[554.9540372],"iteration":389,"passed_time":29.75275428,"remaining_time":16.02071384},
{"learn":[554.9254334],"iteration":390,"passed_time":29.81936484,"remaining_time":15.93925128},
{"learn":[554.8572844],"iteration":391,"passed_time":29.88817693,"remaining_time":15.85903266},
{"learn":[554.8189664],"iteration":392,"passed_time":29.9538115,"remaining_time":15.77719842},
{"learn":[554.7742974],"iteration":393,"passed_time":30.01676834,"remaining_time":15.69404639},
{"learn":[554.7017137],"iteration":394,"passed_time":30.08258615,"remaining_time":15.61248142},
{"learn":[554.6596532],"iteration":395,"passed_time":30.15144279,"remaining_time":15.53256144},
{"learn":[554.507503],"iteration":396,"passed_time":30.21822808,"remaining_time":15.45163803},
{"learn":[554.4350091],"iteration":397,"passed_time":30.29098828,"remaining_time":15.37381817},
{"learn":[554.3781631],"iteration":398,"passed_time":30.36102461,"remaining_time":15.29465149},
{"learn":[554.2825097],"iteration":399,"passed_time":30.43136142,"remaining_time":15.21568071},
{"learn":[554.2196991],"iteration":400,"passed_time":30.49993896,"remaining_time":15.13587993},
{"learn":[554.1910073],"iteration":401,"passed_time":30.56979711,"remaining_time":15.05676574},
{"learn":[554.1066729],"iteration":402,"passed_time":30.64262251,"remaining_time":14.97914798},
{"learn":[554.0817524],"iteration":403,"passed_time":30.71030723,"remaining_time":14.89905994},
{"learn":[554.0161338],"iteration":404,"passed_time":30.78188104,"remaining_time":14.82090569},
{"learn":[553.9717624],"iteration":405,"passed_time":30.87759612,"remaining_time":14.75431933},
{"learn":[553.907677],"iteration":406,"passed_time":30.94760957,"remaining_time":14.67540208},
{"learn":[553.8463124],"iteration":407,"passed_time":31.02283877,"remaining_time":14.59898295},
{"learn":[553.7028711],"iteration":408,"passed_time":31.09900106,"remaining_time":14.52300539},
{"learn":[553.6362663],"iteration":409,"passed_time":31.17890113,"remaining_time":14.44875906},
{"learn":[553.6177247],"iteration":410,"passed_time":31.25673906,"remaining_time":14.37353694},
{"learn":[553.5715293],"iteration":411,"passed_time":31.33672448,"remaining_time":14.29928204},
{"learn":[553.560084],"iteration":412,"passed_time":31.41494889,"remaining_time":14.22420204},
{"learn":[553.5091993],"iteration":413,"passed_time":31.49557471,"remaining_time":14.15018574},
{"learn":[553.4799288],"iteration":414,"passed_time":31.57350602,"remaining_time":14.07493642},
{"learn":[553.4487883],"iteration":415,"passed_time":31.65467726,"remaining_time":14.00110725},
{"learn":[553.3780632],"iteration":416,"passed_time":31.72693967,"remaining_time":13.92333324},
{"learn":[553.3218187],"iteration":417,"passed_time":31.80380644,"remaining_time":13.84759036},
{"learn":[553.2973626],"iteration":418,"passed_time":31.87873564,"remaining_time":13.77100513},
{"learn":[553.2310541],"iteration":419,"passed_time":31.94399699,"remaining_time":13.69028442},
{"learn":[553.1975588],"iteration":420,"passed_time":32.01980105,"remaining_time":13.61411969},
{"learn":[553.1319583],"iteration":421,"passed_time":32.08486663,"remaining_time":13.53342716},
{"learn":[553.0814909],"iteration":422,"passed_time":32.15375369,"remaining_time":13.45440757},
{"learn":[553.0529273],"iteration":423,"passed_time":32.22030315,"remaining_time":13.37446546},
{"learn":[552.989456],"iteration":424,"passed_time":32.29091144,"remaining_time":13.29625765},
{"learn":[552.9606644],"iteration":425,"passed_time":32.36185877,"remaining_time":13.21822401},
{"learn":[552.8648634],"iteration":426,"passed_time":32.43069125,"remaining_time":13.13936671},
{"learn":[552.8236891],"iteration":427,"passed_time":32.49745743,"remaining_time":13.05972588},
{"learn":[552.7801759],"iteration":428,"passed_time":32.56322597,"remaining_time":12.97974741},
{"learn":[552.7548688],"iteration":429,"passed_time":32.63198066,"remaining_time":12.90101561},
{"learn":[552.7054683],"iteration":430,"passed_time":32.69999634,"remaining_time":12.82204033},
{"learn":[552.6837629],"iteration":431,"passed_time":32.76647751,"remaining_time":12.74251903},
{"learn":[552.6470391],"iteration":432,"passed_time":32.84200015,"remaining_time":12.66654509},
{"learn":[552.5976872],"iteration":433,"passed_time":32.91043864,"remaining_time":12.58786363},
{"learn":[552.5585762],"iteration":434,"passed_time":32.97959486,"remaining_time":12.5095015},
{"learn":[552.4929544],"iteration":435,"passed_time":33.0477657,"remaining_time":12.43081095},
{"learn":[552.4474567],"iteration":436,"passed_time":33.11585054,"remaining_time":12.35213647},
{"learn":[552.437393],"iteration":437,"passed_time":33.17861211,"remaining_time":12.27154146},
{"learn":[552.3830085],"iteration":438,"passed_time":33.24334304,"remaining_time":12.19174995},
{"learn":[552.3414721],"iteration":439,"passed_time":33.30740332,"remaining_time":12.11178302},
{"learn":[552.2897256],"iteration":440,"passed_time":33.37488268,"remaining_time":12.03312097},
{"learn":[552.2599054],"iteration":441,"passed_time":33.44476404,"remaining_time":11.95536814},
{"learn":[552.2052664],"iteration":442,"passed_time":33.51305208,"remaining_time":11.87708618},
{"learn":[552.1625035],"iteration":443,"passed_time":33.58362623,"remaining_time":11.79965246},
{"learn":[552.1331481],"iteration":444,"passed_time":33.64745588,"remaining_time":11.71990036},
{"learn":[551.9565852],"iteration":445,"passed_time":33.71436325,"remaining_time":11.64128238},
{"learn":[551.8138487],"iteration":446,"passed_time":33.78078298,"remaining_time":11.56254988},
{"learn":[551.7356504],"iteration":447,"passed_time":33.84808044,"remaining_time":11.48417015},
{"learn":[551.6727579],"iteration":448,"passed_time":33.91225066,"remaining_time":11.40478808},
{"learn":[551.5103817],"iteration":449,"passed_time":33.98266451,"remaining_time":11.32755484},
{"learn":[551.4839609],"iteration":450,"passed_time":34.05952212,"remaining_time":11.2524807},
{"learn":[551.4246038],"iteration":451,"passed_time":34.12936413,"remaining_time":11.17510153},
{"learn":[551.3475359],"iteration":452,"passed_time":34.19609697,"remaining_time":11.0967467},
{"learn":[551.2749539],"iteration":453,"passed_time":34.26746377,"remaining_time":11.01993328},
{"learn":[551.2417342],"iteration":454,"passed_time":34.34118727,"remaining_time":10.94389484},
{"learn":[551.2207016],"iteration":455,"passed_time":34.41042859,"remaining_time":10.86645114},
{"learn":[551.1944701],"iteration":456,"passed_time":34.47436055,"remaining_time":10.78738197},
{"learn":[551.1369976],"iteration":457,"passed_time":34.56837067,"remaining_time":10.71770444},
{"learn":[550.9633982],"iteration":458,"passed_time":34.66383558,"remaining_time":10.64836779},
{"learn":[550.8817691],"iteration":459,"passed_time":34.72598467,"remaining_time":10.56877794},
{"learn":[550.8028359],"iteration":460,"passed_time":34.80745471,"remaining_time":10.49508938},
{"learn":[550.6994954],"iteration":461,"passed_time":34.8873202,"remaining_time":10.42088785},
{"learn":[550.5947287],"iteration":462,"passed_time":34.96400593,"remaining_time":10.34572098},
{"learn":[550.508058],"iteration":463,"passed_time":35.03790759,"remaining_time":10.26973154},
{"learn":[550.4454356],"iteration":464,"passed_time":35.11424598,"remaining_time":10.19445851},
{"learn":[550.3699256],"iteration":465,"passed_time":35.19088019,"remaining_time":10.11926598},
{"learn":[550.2965021],"iteration":466,"passed_time":35.26553949,"remaining_time":10.04350482},
{"learn":[550.2391989],"iteration":467,"passed_time":35.34333191,"remaining_time":9.968632077},
{"learn":[550.2280085],"iteration":468,"passed_time":35.41627149,"remaining_time":9.892391396},
{"learn":[550.2127825],"iteration":469,"passed_time":35.49025702,"remaining_time":9.816454068},
{"learn":[550.20038],"iteration":470,"passed_time":35.56346337,"remaining_time":9.740311623},
{"learn":[550.1351926],"iteration":471,"passed_time":35.64252929,"remaining_time":9.665770655},
{"learn":[550.0512065],"iteration":472,"passed_time":35.71436844,"remaining_time":9.589270173},
{"learn":[550.0376704],"iteration":473,"passed_time":35.79067697,"remaining_time":9.513977423},
{"learn":[549.9768838],"iteration":474,"passed_time":35.86414602,"remaining_time":9.437933162},
{"learn":[549.9029694],"iteration":475,"passed_time":35.93371285,"remaining_time":9.36088318},
{"learn":[549.8936595],"iteration":476,"passed_time":35.9994615,"remaining_time":9.282880009},
{"learn":[549.8368442],"iteration":477,"passed_time":36.0646345,"remaining_time":9.20478119},
{"learn":[549.7819581],"iteration":478,"passed_time":36.1320229,"remaining_time":9.127295972},
{"learn":[549.7084601],"iteration":479,"passed_time":36.1984151,"remaining_time":9.049603775},
{"learn":[549.6591792],"iteration":480,"passed_time":36.26417201,"remaining_time":8.97180139},
{"learn":[549.6458069],"iteration":481,"passed_time":36.32691684,"remaining_time":8.893311591},
{"learn":[549.5998185],"iteration":482,"passed_time":36.39540944,"remaining_time":8.816279305},
{"learn":[549.5919762],"iteration":483,"passed_time":36.46082184,"remaining_time":8.738544077},
{"learn":[549.557867],"iteration":484,"passed_time":36.5263723,"remaining_time":8.660892401},
{"learn":[549.5018362],"iteration":485,"passed_time":36.59199499,"remaining_time":8.583307467},
{"learn":[549.4614744],"iteration":486,"passed_time":36.65996915,"remaining_time":8.506317278},
{"learn":[549.4454447],"iteration":487,"passed_time":36.72469082,"remaining_time":8.428617565},
{"learn":[549.4038289],"iteration":488,"passed_time":36.7918372,"remaining_time":8.351521327},
{"learn":[549.3077742],"iteration":489,"passed_time":36.85882671,"remaining_time":8.274430486},
{"learn":[549.2995422],"iteration":490,"passed_time":36.922257,"remaining_time":8.196590658},
{"learn":[549.2321272],"iteration":491,"passed_time":36.9861901,"remaining_time":8.118919778},
{"learn":[549.135146],"iteration":492,"passed_time":37.05031648,"remaining_time":8.041346578},
{"learn":[549.0685346],"iteration":493,"passed_time":37.11342523,"remaining_time":7.963609461},
{"learn":[549.0370845],"iteration":494,"passed_time":37.18191538,"remaining_time":7.88707296},
{"learn":[548.9702387],"iteration":495,"passed_time":37.25078951,"remaining_time":7.810649413},
{"learn":[548.8357399],"iteration":496,"passed_time":37.31431983,"remaining_time":7.733148778},
{"learn":[548.8277346],"iteration":497,"passed_time":37.38151776,"remaining_time":7.656455446},
{"learn":[548.7578218],"iteration":498,"passed_time":37.46423937,"remaining_time":7.582942237},
{"learn":[548.6906827],"iteration":499,"passed_time":37.54623084,"remaining_time":7.509246167},
{"learn":[548.6829028],"iteration":500,"passed_time":37.61760997,"remaining_time":7.433419934},
{"learn":[548.612485],"iteration":501,"passed_time":37.68620166,"remaining_time":7.357067256},
{"learn":[548.5694928],"iteration":502,"passed_time":37.75927784,"remaining_time":7.28161024},
{"learn":[548.5006344],"iteration":503,"passed_time":37.82296482,"remaining_time":7.204374252},
{"learn":[548.4654627],"iteration":504,"passed_time":37.88846066,"remaining_time":7.127532204},
{"learn":[548.3998811],"iteration":505,"passed_time":37.95357609,"remaining_time":7.050664333},
{"learn":[548.3923174],"iteration":506,"passed_time":38.02937859,"remaining_time":6.975803173},
{"learn":[548.3472903],"iteration":507,"passed_time":38.09484282,"remaining_time":6.899066023},
{"learn":[548.3002022],"iteration":508,"passed_time":38.15935796,"remaining_time":6.822203486},
{"learn":[548.2859374],"iteration":509,"passed_time":38.22403435,"remaining_time":6.745417827},
{"learn":[548.2137656],"iteration":510,"passed_time":38.29213402,"remaining_time":6.669275788},
{"learn":[548.1715454],"iteration":511,"passed_time":38.35688549,"remaining_time":6.592589694},
{"learn":[548.1193459],"iteration":512,"passed_time":38.42414548,"remaining_time":6.51637555},
{"learn":[548.0188669],"iteration":513,"passed_time":38.49079386,"remaining_time":6.440093914},
{"learn":[547.9962874],"iteration":514,"passed_time":38.55677325,"remaining_time":6.363739274},
{"learn":[547.9889341],"iteration":515,"passed_time":38.62084209,"remaining_time":6.287113828},
{"learn":[547.9494936],"iteration":516,"passed_time":38.68484182,"remaining_time":6.210525863},
{"learn":[547.9015858],"iteration":517,"passed_time":38.7537837,"remaining_time":6.134768848},
{"learn":[547.8944372],"iteration":518,"passed_time":38.83345289,"remaining_time":6.060712301},
{"learn":[547.8287641],"iteration":519,"passed_time":38.90589092,"remaining_time":5.98552168},
{"learn":[547.7568189],"iteration":520,"passed_time":38.9819364,"remaining_time":5.910888629},
{"learn":[547.7452097],"iteration":521,"passed_time":39.10515052,"remaining_time":5.843298353},
{"learn":[547.7087942],"iteration":522,"passed_time":39.35266917,"remaining_time":5.793796416},
{"learn":[547.626397],"iteration":523,"passed_time":39.46888977,"remaining_time":5.724495463},
{"learn":[547.5713285],"iteration":524,"passed_time":39.54196364,"remaining_time":5.648851948},
{"learn":[547.56096],"iteration":525,"passed_time":39.61882295,"remaining_time":5.573750758},
{"learn":[547.5541136],"iteration":526,"passed_time":39.69252844,"remaining_time":5.498206027},
{"learn":[547.4992723],"iteration":527,"passed_time":39.76671745,"remaining_time":5.422734197},
{"learn":[547.4926086],"iteration":528,"passed_time":39.83762145,"remaining_time":5.346826319},
{"learn":[547.3945707],"iteration":529,"passed_time":39.90804088,"remaining_time":5.270873324},
{"learn":[547.2810853],"iteration":530,"passed_time":39.97660945,"remaining_time":5.194700663},
{"learn":[547.2193889],"iteration":531,"passed_time":40.04995432,"remaining_time":5.119167094},
{"learn":[547.1514831],"iteration":532,"passed_time":40.11605027,"remaining_time":5.042730522},
{"learn":[547.0942769],"iteration":533,"passed_time":40.17797073,"remaining_time":4.965816607},
{"learn":[546.9885763],"iteration":534,"passed_time":40.24559961,"remaining_time":4.889652289},
{"learn":[546.9815331],"iteration":535,"passed_time":40.30896799,"remaining_time":4.813011103},
{"learn":[546.9683089],"iteration":536,"passed_time":40.37718903,"remaining_time":4.736988658},
{"learn":[546.9614603],"iteration":537,"passed_time":40.43928941,"remaining_time":4.660289858},
{"learn":[546.8950917],"iteration":538,"passed_time":40.50584166,"remaining_time":4.584149056},
{"learn":[546.8585701],"iteration":539,"passed_time":40.56729701,"remaining_time":4.507477445},
{"learn":[546.8041242],"iteration":540,"passed_time":40.63373275,"remaining_time":4.431405236},
{"learn":[546.7200463],"iteration":541,"passed_time":40.69917504,"remaining_time":4.355262274},
{"learn":[546.6346849],"iteration":542,"passed_time":40.76741678,"remaining_time":4.279452591},
{"learn":[546.5333743],"iteration":543,"passed_time":40.83006081,"remaining_time":4.203094495},
{"learn":[546.5047494],"iteration":544,"passed_time":40.89705855,"remaining_time":4.127226093},
{"learn":[546.4347546],"iteration":545,"passed_time":40.96197488,"remaining_time":4.051184329},
{"learn":[546.3706363],"iteration":546,"passed_time":41.02561874,"remaining_time":3.975059951},
{"learn":[546.2769945],"iteration":547,"passed_time":41.09178518,"remaining_time":3.899220491},
{"learn":[546.2532727],"iteration":548,"passed_time":41.15577898,"remaining_time":3.823214441},
{"learn":[546.1926498],"iteration":549,"passed_time":41.22080978,"remaining_time":3.747346344},
{"learn":[546.1237877],"iteration":550,"passed_time":41.28929268,"remaining_time":3.671824576},
{"learn":[546.0652235],"iteration":551,"passed_time":41.36155438,"remaining_time":3.596656903},
{"learn":[546.0591226],"iteration":552,"passed_time":41.43026033,"remaining_time":3.521197532},
{"learn":[545.9762343],"iteration":553,"passed_time":41.49526176,"remaining_time":3.445454947},
{"learn":[545.9242815],"iteration":554,"passed_time":41.5615025,"remaining_time":3.369851554},
{"learn":[545.8994884],"iteration":555,"passed_time":41.62871525,"remaining_time":3.294358761},
{"learn":[545.8016606],"iteration":556,"passed_time":41.69054133,"remaining_time":3.218479851},
{"learn":[545.795289],"iteration":557,"passed_time":41.75541711,"remaining_time":3.142880857},
{"learn":[545.7536339],"iteration":558,"passed_time":41.82823284,"remaining_time":3.067902588},
{"learn":[545.6752454],"iteration":559,"passed_time":41.89359498,"remaining_time":2.992399642},
{"learn":[545.6152085],"iteration":560,"passed_time":41.95785409,"remaining_time":2.916856166},
{"learn":[545.5186597],"iteration":561,"passed_time":42.02746409,"remaining_time":2.841714654},
{"learn":[545.4642215],"iteration":562,"passed_time":42.09251732,"remaining_time":2.766293323},
{"learn":[545.4519066],"iteration":563,"passed_time":42.15685062,"remaining_time":2.690862806},
{"learn":[545.3911049],"iteration":564,"passed_time":42.22389348,"remaining_time":2.615639419},
{"learn":[545.3580543],"iteration":565,"passed_time":42.29024309,"remaining_time":2.540403295},
{"learn":[545.2721152],"iteration":566,"passed_time":42.35435765,"remaining_time":2.465068435},
{"learn":[545.2146186],"iteration":567,"passed_time":42.4256149,"remaining_time":2.390175487},
{"learn":[545.1658373],"iteration":568,"passed_time":42.49557076,"remaining_time":2.315224417},
{"learn":[545.099348],"iteration":569,"passed_time":42.56284251,"remaining_time":2.240149606},
{"learn":[545.0431697],"iteration":570,"passed_time":42.63649343,"remaining_time":2.165426111},
{"learn":[544.9845257],"iteration":571,"passed_time":42.70013842,"remaining_time":2.090216566},
{"learn":[544.8865649],"iteration":572,"passed_time":42.77124998,"remaining_time":2.015399214},
{"learn":[544.7988495],"iteration":573,"passed_time":42.84271929,"remaining_time":1.940610978},
{"learn":[544.7461236],"iteration":574,"passed_time":42.91846994,"remaining_time":1.866020432},
{"learn":[544.7325926],"iteration":575,"passed_time":42.99261043,"remaining_time":1.791358768},
{"learn":[544.6995798],"iteration":576,"passed_time":43.06373151,"remaining_time":1.716578553},
{"learn":[544.6454091],"iteration":577,"passed_time":43.13964267,"remaining_time":1.64199332},
{"learn":[544.6054084],"iteration":578,"passed_time":43.21003562,"remaining_time":1.567203365},
{"learn":[544.5550723],"iteration":579,"passed_time":43.28751984,"remaining_time":1.492673098},
{"learn":[544.503772],"iteration":580,"passed_time":43.37605499,"remaining_time":1.418494053},
{"learn":[544.3637782],"iteration":581,"passed_time":43.45369882,"remaining_time":1.343928829},
{"learn":[544.3354893],"iteration":582,"passed_time":43.539604,"remaining_time":1.269593942},
{"learn":[544.3294833],"iteration":583,"passed_time":43.6465836,"remaining_time":1.195796811},
{"learn":[544.1763676],"iteration":584,"passed_time":43.7294705,"remaining_time":1.121268474},
{"learn":[544.143126],"iteration":585,"passed_time":43.80684745,"remaining_time":1.046579973},
{"learn":[544.0816312],"iteration":586,"passed_time":43.87915458,"remaining_time":0.9717700334},
{"learn":[543.9682014],"iteration":587,"passed_time":43.94644315,"remaining_time":0.8968661866},
{"learn":[543.9150903],"iteration":588,"passed_time":44.01373676,"remaining_time":0.8219882926},
{"learn":[543.8861445],"iteration":589,"passed_time":44.07988055,"remaining_time":0.7471166195},
{"learn":[543.802637],"iteration":590,"passed_time":44.14678924,"remaining_time":0.6722861305},
{"learn":[543.7726919],"iteration":591,"passed_time":44.21321635,"remaining_time":0.5974758967},
{"learn":[543.6756191],"iteration":592,"passed_time":44.27933223,"remaining_time":0.5226902624},
{"learn":[543.5915917],"iteration":593,"passed_time":44.3478607,"remaining_time":0.4479581888},
{"learn":[543.5120392],"iteration":594,"passed_time":44.4126362,"remaining_time":0.3732154303},
{"learn":[543.4614015],"iteration":595,"passed_time":44.64957014,"remaining_time":0.2996615446},
{"learn":[543.3853559],"iteration":596,"passed_time":44.7527712,"remaining_time":0.2248882975},
{"learn":[543.3568786],"iteration":597,"passed_time":44.81812301,"remaining_time":0.149893388},
{"learn":[543.3110801],"iteration":598,"passed_time":44.88288835,"remaining_time":0.07492969674},
{"learn":[543.2550255],"iteration":599,"passed_time":44.94818924,"remaining_time":0}
]}